Workbook

Sheet Cover
B2: Spending Is Data: A 30-Day Pattern Recognition Course
B4: C3 Action Workbook
B6: Six worksheets that build your personal Cut, Cancel, and Combine action plan.
B8: Tab Navigation Guide
B10: Numbers Snapshot — Capture your income, expenses, and subscriptions at a glance.
B12: C3 First Look — Tag each subscription with your first instinct: Keep, Cut, Cancel, or Combine.
B14: Cut List — Document spending habits you want to reduce in frequency.
B16: Cancel List — List subscriptions and services to stop or downgrade.
B18: Combine List — Find consolidation, sharing, and replacement opportunities.
B20: C3 Action Plan — Pull all three strategies together into one sequenced plan.

Sheet Numbers Snapshot
A1: Numbers Snapshot
A2: Section 1 — Income
A3: Enter each income source and its monthly amount.
A4: Income Source | B4: Monthly Amount
A10: Total Income | B10: =SUM(B5:B9)
A12: Section 2 — Fixed Expenses
A13: List your fixed monthly expenses (rent, utilities, insurance, etc.).
A14: Expense Name | B14: Monthly Amount
A27: Total Fixed Expenses | B27: =SUM(B15:B26)
A29: Section 3 — Variable Spending
A30: Enter your typical monthly spend for each category.
A31: Category | B31: Monthly Amount
A32: Groceries
A33: Dining out / takeout
A34: Entertainment
A35: Shopping (clothing + household)
A36: Personal care
A37: Subscriptions
A38: Other
A39: Total Variable Spending | B39: =SUM(B32:B38)
A41: Section 4 — Subscription Audit
A42: List every subscription you pay for. Mark Y if you use it regularly, N if you don't.
A43: Subscription Name | B43: Monthly Cost | C43: Use Regularly (Y/N)
A59: Total Monthly Subscriptions | B59: =SUM(B44:B58) | C59: ="Total monthly subscriptions: $"&TEXT(B59,"#,##0.00")
A61: Section 5 — Summary
A62: Total In | B62: =B10
A63: Total Fixed | B63: =B27
A64: Total Variable | B64: =B39
A65: Total Subscriptions | B65: =B59
A66: Estimated Monthly Surplus/Gap | B66: =B10-B27-B39

Sheet C3 First Look
A1: C3 First Look
A2: This is a first-instinct pass — no commitments required. Tag each subscription with Keep, Cut, Cancel, or Combine.
A3: Subscription Name | B3: Monthly Cost | C3: First Instinct | D3: Notes
A4: ='Numbers Snapshot'!A44 | B4: ='Numbers Snapshot'!B44
A5: ='Numbers Snapshot'!A45 | B5: ='Numbers Snapshot'!B45
A6: ='Numbers Snapshot'!A46 | B6: ='Numbers Snapshot'!B46
A7: ='Numbers Snapshot'!A47 | B7: ='Numbers Snapshot'!B47
A8: ='Numbers Snapshot'!A48 | B8: ='Numbers Snapshot'!B48
A9: ='Numbers Snapshot'!A49 | B9: ='Numbers Snapshot'!B49
A10: ='Numbers Snapshot'!A50 | B10: ='Numbers Snapshot'!B50
A11: ='Numbers Snapshot'!A51 | B11: ='Numbers Snapshot'!B51
A12: ='Numbers Snapshot'!A52 | B12: ='Numbers Snapshot'!B52
A13: ='Numbers Snapshot'!A53 | B13: ='Numbers Snapshot'!B53
A14: ='Numbers Snapshot'!A54 | B14: ='Numbers Snapshot'!B54
A15: ='Numbers Snapshot'!A55 | B15: ='Numbers Snapshot'!B55
... A18: ='Numbers Snapshot'!A58 | B18: ='Numbers Snapshot'!B58
A20: Summary
A21: Count of rows marked Cancel | C21: =COUNTIF(C4:C18,"Cancel")
A22: Total estimated monthly savings if all Cancel rows were acted on | C22: =SUMIF(C4:C18,"Cancel",B4:B18)
A24: ="If you canceled everything marked Cancel: $"&TEXT(SUMIF(C4:C18,"Cancel",B4:B18),"#,##0.00")&"/month"

Sheet Cut List
A1: Cut List
A2: Document spending habits to reduce in frequency, not eliminate entirely.
A3: Spending Habit | B3: Current Frequency | C3: Cut Target | D3: How/When I Will Decide (day, time, or context) | E3: Estimated Monthly Savings
A15: Total estimated monthly savings from cuts | E15: =SUM(E4:E13)
A17: ="Total estimated monthly savings from cuts: $"&TEXT(E15,"#,##0.00")
A19: Which Chasing Pattern shows up most in my Cut list:
A22: The one cut I am starting this week:

Sheet Cancel List
A1: Cancel List
A2: Document subscriptions and services to stop entirely or downgrade.
A3: Table 1 — Full Cancels
A4: Subscription / Service | B4: Monthly Cost | C4: Last Time I Used It | D4: Target Cancel Date
A15: Total monthly recovery from full cancels | B15: =SUM(B5:B14)
A17: Table 2 — Downgrades
A18: Subscription / Service | B18: Current Cost | C18: Free or Lower Tier (Y/N) | D18: Notes
A27: Total monthly reduction from downgrades | B27: =SUM(B19:B26)
A29: Combined Summary
A30: Combined monthly recovery | B30: =B15+B27
A32: The cancel I keep putting off, and why:

Sheet Combine List
A1: Combine List
A2: Document consolidation, sharing, and replacement opportunities.
A3: Table 1 — Consolidation
A4: Current Setup (multiple tools) | B4: What to Consolidate Into | C4: Monthly Savings
A11: Total Consolidation Savings | C11: =SUM(C5:C10)
A13: Table 2 — Sharing
A14: Service / Subscription | B14: Could Share With | C14: Potential Monthly Savings
A21: Total Sharing Savings | C21: =SUM(C15:C20)
A23: Table 3 — Replacement
A24: Current Expensive Option | B24: Cheaper Alternative That Does the Same Job | C24: Monthly Savings
A31: Total Replacement Savings | C31: =SUM(C25:C30)
A33: ="Total estimated monthly savings from Combine strategies: $"&TEXT(C11+C21+C31,"#,##0.00")
A34: Total Combine Savings (numeric) | C34: =C11+C21+C31

Sheet C3 Action Plan
A1: C3 Action Plan
A2: Your complete C3 strategy — all values pull automatically from your Cut, Cancel, and Combine tabs.
A3: Section 1 — The Math
A4: Monthly savings from Cut | B4: ='Cut List'!E15
A5: Monthly savings from Cancel | B5: ='Cancel List'!B30
A6: Monthly savings from Combine | B6: ='Combine List'!C34
A7: Total monthly recovery | B7: ='Cut List'!E15+'Cancel List'!B30+'Combine List'!C34
A8: Projected annual recovery | B8: =B7*12
A10: Section 2 — Pattern to Strategy
A11: My Active Pattern | B11: C3 Strategy That Fits | C11: What That Looks Like for Me
A17: Section 3 — Action Sequence
A18: This Week (Days 15 to 21)
A19: Item | B19: Date
A26: By End of Challenge (Day 30)
A27: Item | B27: Date
A34: After the Challenge
A35: Item | B35: Date
A42: Section 4 — One Sentence
A43: In one sentence, what I am changing and why:
