Workbook

Sheet Dashboard
B2: 30-Day No-Spend Challenge
B3: Personal spending awareness and pattern recognition
B6: Key Metrics
B8: Active Monthly Subscriptions | D8: ='Subscriptions'!C14
B9: Freed Up This Month | D9: ='Freed Money Plan'!B8
B10: Highest Category | D10: =MAX('Categories'!D2:D10)
B13: Tabs
B15: → Subscriptions
B16: → One-Time Purchases
B17: → Categories
B18: → Monthly
B19: → Weekly
B20: → Before/After
B21: → Freed Money Plan
B22: → README

Sheet README
B2: How to Use This Workbook
B5: 1. Make a copy first (File → Save As)
B6: 2. Start with Subscriptions tab — enter your streaming, apps, memberships
B7: 3. Log one-time purchases in One-Time Purchases tab
B8: 4. Categories and Dashboard update automatically
B9: 5. Use Freed Money Plan to allocate savings from cancelled subscriptions
B11: The Chasing Patterns help you see WHY you spend:
B12: Rainbows — chasing the solution that will fix everything
B13: Ambrosia — spending to change how you feel
B14: Sunshine — little mood boosts that add up
B15: Stardust — buying to feel more legit/polished
B16: Unicorns — comparing yourself to others
B17: Moonbeams — fantasy purchases for someday

Sheet Subscriptions
A1: Service | B1: Category | C1: Monthly | D1: Annual | E1: Status | F1: Decision | G1: Last Used | H1: Notes
A2: Netflix | B2: Entertainment | C2: 15.49 | D2: =C2*12 | E2: Active | F2: Evaluate | G2: Weekly | H2: Do we need Premium?
A3: Spotify Premium | B3: Entertainment | C3: 10.99 | D3: =C3*12 | E3: Active | F3: Keep | G3: Daily | H3: Use constantly
A4: Amazon Prime | B4: Shopping | C4: 14.99 | D4: =C4*12 | E4: Active | F4: Keep | G4: Weekly | H4: Shipping + video
A5: Hulu | B5: Entertainment | C5: 17.99 | D5: =C5*12 | E5: Active | F5: Cancel | G5: Rarely | H5: Overlap with Netflix
A6: Planet Fitness | B6: Health | C6: 24.99 | D6: =C6*12 | E6: Active | F6: Evaluate | G6: Monthly | H6: Going 2x/month max
A7: HelloFresh | B7: Food | C7: 69.99 | D7: =C7*12 | E7: Active | F7: Pause | G7: Skipping often | H7: Boxes piling up
A8: Headspace | B8: Wellness | C8: 12.99 | D8: =C8*12 | E8: Active | F8: Keep | G8: Daily | H8: Morning routine
A9: iCloud Storage | B9: Tech | C9: 2.99 | D9: =C9*12 | E9: Active | F9: Keep | G9: Always | H9: Photo backup
A10: YouTube Premium | B10: Entertainment | C10: 13.99 | D10: =C10*12 | E10: Active | F10: Cancel | G10: Sometimes | H10: Ads aren't that bad
A11: DoorDash DashPass | B11: Food | C11: 9.99 | D11: =C11*12 | E11: Active | F11: Cancel | G11: Weekly | H11: Enables impulse orders
A12: Audible | B12: Entertainment | C12: 14.95 | D12: =C12*12 | E12: Active | F12: Pause | G12: Monthly | H12: 6 unused credits
B14: TOTAL | C14: =SUM(C2:C12) | D14: =SUM(D2:D12)

Sheet One-Time Purchases
A1: Date | B1: Item | C1: Category | D1: Amount | E1: Essential? | F1: Pattern | G1: Notes
A2: 45660 | B2: Winter coat | C2: Clothing | D2: 89.99 | E2: Yes | G2: Old one ripped
A3: 45662 | B3: Starbucks x3 | C3: Food | D3: 18.75 | E3: No | F3: Sunshine | G3: Treating myself
A4: 45665 | B4: Target run extras | C4: Shopping | D4: 67.5 | E4: No | F4: Ambrosia | G4: Went for toothpaste
A5: 45669 | B5: Instagram ad leggings | C5: Clothing | D5: 48 | E5: No | F5: Rainbows | G5: Algorithm got me
A6: 45672 | B6: New planner | C6: Supplies | D6: 32 | E6: No | F6: Ambrosia | G6: Fresh start energy
A7: 45675 | B7: Takeout comfort food | C7: Food | D7: 42 | E7: No | F7: Ambrosia | G7: Bad day
A8: 45679 | B8: Skincare from TikTok | C8: Beauty | D8: 65 | E8: No | F8: Stardust | G8: Influencer rec
C10: TOTAL | D10: =SUM(D2:D8)

Sheet Categories
A1: Category | B1: Subscriptions | C1: One-Time | D1: Total | E1: % of Total
A2: Entertainment | B2: =SUMIF(Subscriptions!B:B,"Entertainment",Subscriptions!C:C) | C2: =SUMIF('One-Time Purchases'!C:C,"Entertainment",'One-Time Purchases'!D:D) | D2: =B2+C2 | E2: =IF(D$12=0,0,D2/D$12)
A3: Food | B3: =SUMIF(Subscriptions!B:B,"Food",Subscriptions!C:C) | C3: =SUMIF('One-Time Purchases'!C:C,"Food",'One-Time Purchases'!D:D) | D3: =B3+C3 | E3: =IF(D$12=0,0,D3/D$12)
A4: Health | B4: =SUMIF(Subscriptions!B:B,"Health",Subscriptions!C:C) | C4: =SUMIF('One-Time Purchases'!C:C,"Health",'One-Time Purchases'!D:D) | D4: =B4+C4 | E4: =IF(D$12=0,0,D4/D$12)
A5: Wellness | B5: =SUMIF(Subscriptions!B:B,"Wellness",Subscriptions!C:C) | C5: =SUMIF('One-Time Purchases'!C:C,"Wellness",'One-Time Purchases'!D:D) | D5: =B5+C5 | E5: =IF(D$12=0,0,D5/D$12)
A6: Shopping | B6: =SUMIF(Subscriptions!B:B,"Shopping",Subscriptions!C:C) | C6: =SUMIF('One-Time Purchases'!C:C,"Shopping",'One-Time Purchases'!D:D) | D6: =B6+C6 | E6: =IF(D$12=0,0,D6/D$12)
A7: Tech | B7: =SUMIF(Subscriptions!B:B,"Tech",Subscriptions!C:C) | C7: =SUMIF('One-Time Purchases'!C:C,"Tech",'One-Time Purchases'!D:D) | D7: =B7+C7 | E7: =IF(D$12=0,0,D7/D$12)
A8: Clothing | B8: =SUMIF(Subscriptions!B:B,"Clothing",Subscriptions!C:C) | C8: =SUMIF('One-Time Purchases'!C:C,"Clothing",'One-Time Purchases'!D:D) | D8: =B8+C8 | E8: =IF(D$12=0,0,D8/D$12)
A9: Beauty | B9: =SUMIF(Subscriptions!B:B,"Beauty",Subscriptions!C:C) | C9: =SUMIF('One-Time Purchases'!C:C,"Beauty",'One-Time Purchases'!D:D) | D9: =B9+C9 | E9: =IF(D$12=0,0,D9/D$12)
A10: Supplies | B10: =SUMIF(Subscriptions!B:B,"Supplies",Subscriptions!C:C) | C10: =SUMIF('One-Time Purchases'!C:C,"Supplies",'One-Time Purchases'!D:D) | D10: =B10+C10 | E10: =IF(D$12=0,0,D10/D$12)
A12: TOTAL | B12: =SUM(B2:B10) | C12: =SUM(C2:C10) | D12: =SUM(D2:D10)

Sheet Monthly
A1: Month | B1: Income | C1: Essential | D1: Non-Essential | E1: Net | F1: Savings Rate
A2: Jan 2025 | B2: 4200 | C2: 2800 | D2: 685 | E2: =B2-C2-D2 | F2: =IF(B2=0,0,E2/B2)
A3: Feb 2025 | B3: 4200 | C3: 2750 | D3: 420 | E3: =B3-C3-D3 | F3: =IF(B3=0,0,E3/B3)
A4: Mar 2025 | B4: 4350 | C4: 2800 | D4: 310 | E4: =B4-C4-D4 | F4: =IF(B4=0,0,E4/B4)

Sheet Weekly
A1: Week | B1: Start | C1: End | D1: Income | E1: Expenses | F1: Net | G1: No-Spend Days
A2: Week 1 | B2: 45658 | C2: 45664 | D2: 1050 | E2: 780 | F2: =D2-E2 | G2: 3
A3: Week 2 | B3: 45665 | C3: 45671 | D3: 1050 | E3: 620 | F3: =D3-E3 | G3: 4
A4: Week 3 | B4: 45672 | C4: 45678 | D4: 1050 | E4: 540 | F4: =D4-E4 | G4: 5
A5: Week 4 | B5: 45679 | C5: 45685 | D5: 1050 | E5: 485 | F5: =D5-E5 | G5: 5
F7: Total No-Spend: | G7: =SUM(G2:G5)

Sheet Before-After
A1: Metric | B1: Before | C1: After | D1: Change | E1: % Change
A2: Monthly Subscriptions | B2: 209.34 | C2: 147.43 | D2: =C2-B2 | E2: =IF(B2=0,0,(C2-B2)/B2)
A3: Active Subscriptions | B3: 11 | C3: 7 | D3: =C3-B3 | E3: =IF(B3=0,0,(C3-B3)/B3)
A4: Weekly Non-Essential Avg | B4: 165 | C4: 85 | D4: =C4-B4 | E4: =IF(B4=0,0,(C4-B4)/B4)
A5: Monthly Savings Rate | B5: 0.12 | C5: 0.24 | D5: =C5-B5 | E5: =IF(B5=0,0,(C5-B5)/B5)
A6: No-Spend Days/Month | B6: 6 | C6: 17 | D6: =C6-B6 | E6: =IF(B6=0,0,(C6-B6)/B6)

Sheet Freed Money Plan
A1: Cancelled/Paused | B1: Monthly $ | C1: New Allocation | D1: Purpose
A2: Hulu | B2: 17.99 | C2: Emergency Fund | D2: Building 3mo buffer
A3: HelloFresh | B3: 69.99 | C3: Debt Payoff | D3: Credit card
A4: YouTube Premium | B4: 13.99 | C4: Savings | D4: Vacation fund
A5: DoorDash DashPass | B5: 9.99 | C5: Savings | D5: Future me fund
A6: Audible | B6: 14.95 | C6: Debt Payoff | D6: Student loan extra
A8: TOTAL FREED | B8: =SUM(B2:B6)
